{"nodes": [{"id": "assets_sprites_ui_skill_q_asset", "label": "Skill Icon: Q (Ice Shard)", "file_type": "image", "source_file": "assets/sprites/ui/skill_q.png", "source_location": null, "source_url": null, "captured_at": null, "author": null, "contributor": null}, {"id": "concept_ice_frost_shard_motif", "label": "Ice/Frost Shard Visual Motif", "file_type": "concept", "source_file": "assets/sprites/ui/skill_q.png", "source_location": null, "source_url": null, "captured_at": null, "author": null, "contributor": null}, {"id": "concept_ornate_skill_icon_frame_style", "label": "Ornate Dark-Stone Skill Icon Frame Style", "file_type": "concept", "source_file": "assets/sprites/ui/skill_q.png", "source_location": null, "source_url": null, "captured_at": null, "author": null, "contributor": null}, {"id": "concept_q_hotbar_slot", "label": "Q Hotbar Slot", "file_type": "concept", "source_file": "assets/sprites/ui/skill_q.png", "source_location": null, "source_url": null, "captured_at": null, "author": null, "contributor": null}, {"id": "assets_sprites_ui_skill_q_asset", "label": "Skill Q Icon", "file_type": "image", "source_file": "assets/sprites/ui/skill_q.png", "source_location": null, "source_url": null, "captured_at": null, "author": null, "contributor": null}], "edges": [{"source": "assets_sprites_ui_skill_q_asset", "target": "concept_q_hotbar_slot", "relation": "references", "confidence": "EXTRACTED", "confidence_score": 1.0, "source_file": "assets/sprites/ui/skill_q.png", "source_location": null, "weight": 1.0}, {"source": "assets_sprites_ui_skill_q_asset", "target": "concept_ice_frost_shard_motif", "relation": "conceptually_related_to", "confidence": "INFERRED", "confidence_score": 0.85, "source_file": "assets/sprites/ui/skill_q.png", "source_location": null, "weight": 1.0}, {"source": "assets_sprites_ui_skill_q_asset", "target": "concept_ornate_skill_icon_frame_style", "relation": "conceptually_related_to", "confidence": "INFERRED", "confidence_score": 0.85, "source_file": "assets/sprites/ui/skill_q.png", "source_location": null, "weight": 1.0}], "hyperedges": []}