{"nodes": [{"id": "scenes_ui_hud_hud", "label": "hud.gd", "file_type": "code", "source_file": "scenes/ui/hud.gd", "source_location": null, "source_url": null, "captured_at": null, "author": null, "contributor": null}, {"id": "scenes_ui_hud__ready", "label": "_ready()", "file_type": "code", "source_file": "scenes/ui/hud.gd", "source_location": null, "source_url": null, "captured_at": null, "author": null, "contributor": null}, {"id": "scenes_ui_hud__process", "label": "_process(delta)", "file_type": "code", "source_file": "scenes/ui/hud.gd", "source_location": null, "source_url": null, "captured_at": null, "author": null, "contributor": null}, {"id": "scenes_ui_hud__on_health_changed", "label": "_on_health_changed(current, max_health)", "file_type": "code", "source_file": "scenes/ui/hud.gd", "source_location": null, "source_url": null, "captured_at": null, "author": null, "contributor": null}, {"id": "scenes_ui_hud__on_mana_changed", "label": "_on_mana_changed(current, max_mana)", "file_type": "code", "source_file": "scenes/ui/hud.gd", "source_location": null, "source_url": null, "captured_at": null, "author": null, "contributor": null}, {"id": "scenes_ui_hud__on_cooldown_started", "label": "_on_cooldown_started(slot, duration)", "file_type": "code", "source_file": "scenes/ui/hud.gd", "source_location": null, "source_url": null, "captured_at": null, "author": null, "contributor": null}, {"id": "scenes_ui_hud__on_wave_started", "label": "_on_wave_started(wave, is_boss)", "file_type": "code", "source_file": "scenes/ui/hud.gd", "source_location": null, "source_url": null, "captured_at": null, "author": null, "contributor": null}, {"id": "scenes_ui_hud__on_victory", "label": "_on_victory()", "file_type": "code", "source_file": "scenes/ui/hud.gd", "source_location": null, "source_url": null, "captured_at": null, "author": null, "contributor": null}, {"id": "scenes_ui_hud__flash_banner", "label": "_flash_banner(text, color, hold)", "file_type": "code", "source_file": "scenes/ui/hud.gd", "source_location": null, "source_url": null, "captured_at": null, "author": null, "contributor": null}, {"id": "scenes_ui_hud__on_settings_pressed", "label": "_on_settings_pressed()", "file_type": "code", "source_file": "scenes/ui/hud.gd", "source_location": null, "source_url": null, "captured_at": null, "author": null, "contributor": null}], "edges": [{"source": "scenes_ui_hud_hud", "target": "canvaslayer", "relation": "implements", "confidence": "EXTRACTED", "confidence_score": 1.0, "source_file": "scenes/ui/hud.gd", "source_location": null, "weight": 1.0}, {"source": "scenes_ui_hud__ready", "target": "scenes_ui_hud__on_settings_pressed", "relation": "calls", "confidence": "EXTRACTED", "confidence_score": 1.0, "source_file": "scenes/ui/hud.gd", "source_location": null, "weight": 1.0}, {"source": "scenes_ui_hud__on_wave_started", "target": "scenes_ui_hud__flash_banner", "relation": "calls", "confidence": "EXTRACTED", "confidence_score": 1.0, "source_file": "scenes/ui/hud.gd", "source_location": null, "weight": 1.0}, {"source": "scenes_ui_hud__on_victory", "target": "scenes_ui_hud__flash_banner", "relation": "calls", "confidence": "EXTRACTED", "confidence_score": 1.0, "source_file": "scenes/ui/hud.gd", "source_location": null, "weight": 1.0}, {"source": "scenes_ui_hud__on_settings_pressed", "target": "scenes_ui_settings_menu_toggle_menu", "relation": "calls", "confidence": "EXTRACTED", "confidence_score": 1.0, "source_file": "scenes/ui/hud.gd", "source_location": null, "weight": 1.0}, {"source": "scripts_systems_event_bus_player_health_changed", "target": "scenes_ui_hud__on_health_changed", "relation": "calls", "confidence": "EXTRACTED", "confidence_score": 1.0, "source_file": "scenes/ui/hud.gd", "source_location": null, "weight": 1.0}, {"source": "scripts_systems_event_bus_player_mana_changed", "target": "scenes_ui_hud__on_mana_changed", "relation": "calls", "confidence": "EXTRACTED", "confidence_score": 1.0, "source_file": "scenes/ui/hud.gd", "source_location": null, "weight": 1.0}, {"source": "scripts_systems_event_bus_skill_cooldown_started", "target": "scenes_ui_hud__on_cooldown_started", "relation": "calls", "confidence": "EXTRACTED", "confidence_score": 1.0, "source_file": "scenes/ui/hud.gd", "source_location": null, "weight": 1.0}, {"source": "scripts_systems_event_bus_wave_started", "target": "scenes_ui_hud__on_wave_started", "relation": "calls", "confidence": "EXTRACTED", "confidence_score": 1.0, "source_file": "scenes/ui/hud.gd", "source_location": null, "weight": 1.0}, {"source": "scripts_systems_event_bus_victory", "target": "scenes_ui_hud__on_victory", "relation": "calls", "confidence": "EXTRACTED", "confidence_score": 1.0, "source_file": "scenes/ui/hud.gd", "source_location": null, "weight": 1.0}, {"source": "scenes_ui_hud_hud", "target": "scripts_systems_wave_manager_wave_manager", "relation": "shares_data_with", "confidence": "INFERRED", "confidence_score": 0.95, "source_file": "scenes/ui/hud.gd", "source_location": null, "weight": 1.0}], "hyperedges": []}